spotifywebapi/__init__.py
spotifywebapi/client.py
spotifywebapi/exceptions.py
spotifywebapi/user.py
spotifywebapi-1.2.8.dist-info/LICENSE
spotifywebapi-1.2.8.dist-info/METADATA
spotifywebapi-1.2.8.dist-info/WHEEL
spotifywebapi-1.2.8.dist-info/top_level.txt
spotifywebapi-1.2.8.dist-info/RECORD
