Metadata-Version: 2.1
Name: spotifywebapi
Version: 1.2.8
Summary: A simple Spotify Web API in Python
Home-page: https://github.com/Firius0408/spotifywebapi
Author: Brian Cheng
Author-email: briantc@mit.edu
License: UNKNOWN
Platform: UNKNOWN
Classifier: Programming Language :: Python :: 3
Classifier: License :: OSI Approved :: MIT License
Classifier: Operating System :: OS Independent
Requires-Python: >=3.6
License-File: LICENSE
Requires-Dist: requests
